MANIFEST.in
setup.cfg
setup.py
cte_tree/__init__.py
cte_tree/fields.py
cte_tree/models.py
cte_tree/query.py
cte_tree/tests.py
cte_tree/views.py
cte_tree_test/__init__.py
cte_tree_test/fields.py
cte_tree_test/manage.py
cte_tree_test/models.py
cte_tree_test/settings.py
cte_tree_test/tests.py
django_cte_trees_python3.egg-info/PKG-INFO
django_cte_trees_python3.egg-info/SOURCES.txt
django_cte_trees_python3.egg-info/dependency_links.txt
django_cte_trees_python3.egg-info/top_level.txt
django_cte_trees_python3.egg-info/zip-safe
docs/source/advanced.rst
docs/source/api.rst
docs/source/basic.rst
docs/source/conf.py
docs/source/examples.rst
docs/source/index.rst
docs/source/technical.rst