Metadata-Version: 1.1
Name: django-cte-trees-python3
Version: 1.0.2
Summary: Django Adjacency-List trees using PostgreSQL Common Table Expressions (CTE).
Home-page: https://github.com/stjosephcontent/django-cte-trees
Author: David Hoffman
Author-email: david.hoffman@stjoseph.com
License: BSD
Download-URL: https://github.com/stjosephcontent/django-cte-trees/archive/master.zip
Keywords: django,postgresql,cte,trees,sql
Platform: UNKNOWN
Classifier: Development Status :: 3 - Alpha
Classifier: Environment :: Web Environment
Classifier: Framework :: Django
Classifier: Intended Audience :: Developers
Classifier: License :: OSI Approved :: BSD License
Classifier: Operating System :: OS Independent
Classifier: Programming Language :: Python
Classifier: Topic :: Software Development :: Libraries :: Python Modules
